rc_entry.py
mkclus/__init__.py
mkclus/head_of_clustering.py
mkclus/prepare_datasets.py
mkclus/visualise_clusters.py
reporth-2.6.1.dist-info/LICENSE
reporth-2.6.1.dist-info/METADATA
reporth-2.6.1.dist-info/WHEEL
reporth-2.6.1.dist-info/entry_points.txt
reporth-2.6.1.dist-info/top_level.txt
reporth-2.6.1.dist-info/RECORD
