Metadata-Version: 2.1
Name: reporth
Version: 2.6.1
Summary: Cluster DNA Sequences based on orthology
Home-page: https://github.com/blackthorne18/reporth_cli
Author: Prajwal Bharadwaj
License: UNKNOWN
Platform: UNKNOWN
Classifier: Programming Language :: Python :: 3.10
Classifier: Operating System :: OS Independent
Requires-Python: >=3.10
License-File: LICENSE
Requires-Dist: click (>=8.1.3)
Requires-Dist: biopython (>=1.79)
Requires-Dist: networkx (>=2.8.8)
Requires-Dist: Levenshtein (>=0.20.8)
Requires-Dist: numpy (>=1.23.3)
